Workbook

Sheet Read Me
A1: ADT Revamp — Page Design Reference Sheet
A2: Analysis of C:\Users\Gopal\Desktop\ADT_Revamp (Opendhi ADT — EOR / PEO / Immigration / Contractor workforce platform prototype). Prepared 19 Oct 2026 from a full read of index.html, 40 CSS and 32 JS files (~44k lines), including the design rationale written in code comments.
A4: What this workbook is | B4: Every page, sub-view and major flow in the project, with the design pattern it uses, the well-known product / design system that pattern is taken from or closest to, and why that design suits the page and its users.
A5: Pages & views documented | B5: =COUNTA('Page Design Map'!C5:C500) -> 88
A6: Modules covered | B6: Global shell · Dashboard (10 role views) · People · Contracts · HR Docs · Time & Attendance · Payroll · Finance · Compliance Hub · Administration · Admin Access · Support · AI Executive & Configure (not in sidebar)
A7: Overall design direction | B7: One monochrome "ink on white" system: Inter typeface, near-black primary (#1a1a1a), Tailwind slate neutrals, five semantic status tones and an 8-step contract pipeline ladder. Behaviour borrows from Linear (restraint, Cmd-K, side panels), information architecture from Rippling / Deel, listing conventions from enterprise admin tables (Ant ProTable), and HR / time / payroll vocabulary from Indian HRMS products (Keka, greytHR, Darwinbox, Zoho People).
A8: The standard page shell | B8: Filter bar ("Select Filter") + count tiles that double as status filters → table with S.No and pinned Action column → right-side detail panel with tabs Basic Details / Logs / History / (Attachments) / Workflow. Creation always happens in an 880px popup form. Status changes always go through Logs with a mandatory comment.
A9: Tabs in this workbook | B9: Page Design Map — one row per page/view (main sheet). Design System — the standardised components every page reuses. Design Tokens — colours, type, radii, motion values. Reference Index — each reference product and how many pages draw on it. Observations — inconsistencies and follow-ups found during analysis.
A10: How to read "Design Reference" | B10: The products named are the closest well-known source for that layout or interaction, based on evidence in the markup, class names and code comments. ADT does not copy any product's branding; the references explain the lineage of each pattern.
A11: Column "Design rules seen in code" | B11: Short quotes or paraphrases of the design rationale the team wrote into the source code comments for that page.

Sheet Page Design Map
A1: Page Design Map — every page, its design source and why it fits
A2: One row per page, sub-view or major flow. Section colours: grey = global shell, blue = overview, green = workforce, amber = time & pay, violet = governance, cyan = support, red = AI & configure (built but not linked from the sidebar).
A4: # | B4: Section | C4: Module | D4: Page / View | E4: Page ID / Route | F4: How it is reached | G4: Primary user(s) | H4: Design pattern used (layout & key components) | I4: Design reference — taken from | J4: Why this design suits the page & use case | K4: Design rules seen in code | L4: Main source files
A5: 1 | B5: Global Shell | C5: App Frame | D5: Top Bar (title, page "+", role switcher, search, bell, entity, user menu) | E5: — (every page) | F5: Always visible | G5: All users | H5: 56px white bar. Logo strip = rail width so title aligns with content gutter. Page title + round black "+" Add for the current page + contextual page buttons (Cost Calculator on EOR/PEO, Calendar on Holidays). Right: "Logged in as" role menu with capability sub-lines, Ctrl+K search, bell with red dot, entity menu, avatar menu (profile, Apply Application, demo switches, Sign out). Popovers grow from their anchor. | I5: Stripe Dashboard / Linear app header; Stripe & Deel account (entity) switcher; Salesforce "Log in as" for the role switcher | J5: Every global control lives in one predictable strip, so page content stays focused on work. The contextual "+" and tool buttons put the main create action where the eye already is. The role switcher lets stakeholders demo role-gated flows (HR, Compliance, IT, Finance, Manager, Employee) without logging out. | K5: Page actions are contextual — Cost Calculator only on EOR/PEO listings ("an immigration case is priced on government fees"). Role sub-lines document RBAC inline. | L5: index.html, js/core.js (setAppRole), js/renderer.js
A6: 2 | B6: Global Shell | C6: App Frame | D6: Sidebar Navigation (grouped rail) | E6: — (sidebarItems) | F6: Always visible | G6: All users | H6: 224px rail, collapses to 62px icon rail; auto-folds at ≤1024px and overlays on phones. Uppercase section labels (Overview, Workforce, Time & Pay, Governance, Support), accordion groups (one open at a time), children behind a 2px guide line, active item = 3px ink bar + slate fill. Monochrome 15px stroke icons with one-shot hover animations (clock hand sweeps, gear turns). | I6: Rippling / Deel information architecture + Atlassian side-navigation mechanics (sections, collapsible groups, icon rail) | J6: An EOR platform has 25+ destinations; grouping by what the user is doing (not by department) lets every role find their area quickly. The collapsible rail gives wide tables more room, which matters for dense HR listings. | K6: "Grouped by what the user is doing, not by which team owns the screen." A section header only if it holds more than one module; a dropdown only if it holds more than one page. | L6: js/core.js (sidebarItems, buildSidebar), css/main.css, css/sidebar-icons.css
A7: 3 | B7: Global Shell | C7: App Frame | D7: Global Search / Command Palette (Ctrl+K) | E7: #search-overlay | F7: Top bar search icon, Ctrl/Cmd+K | G7: All users | H7: Centred 560px card over a blurred backdrop. Results grouped: Go to (built from the sidebar itself), Queues (pre-filtered lists e.g. Pending leave requests, Unpaid invoices, Open tickets), Create (open create forms), Tools. Ranking: prefix > word-start > anywhere. Arrow keys / Enter / Esc with a <kbd> hint footer; "Open" vs "Run" labels. | I7: Linear / Raycast / Superhuman command palette | J7: With 40+ destinations in nested groups, two keystrokes reach anything. Queue entries "land on the work, not on the page", skipping the navigate-then-filter step power users repeat daily. | K7: "Destinations come from the rail itself" — so the palette can never go stale. "It doubles as the product's index." | L7: js/renderer.js (openSearch, PALETTE_EXTRA), css/quick-actions.css
A8: 4 | B8: Global Shell | C8: App Frame | D8: Notifications Popover | E8: #notif-pop | F8: Bell icon | G8: All users | H8: 380px card under the bell: Refresh/Close icon buttons, "Mark all as read", "Only Show Unread" switch (on by default), rows with avatar, text, time, Contract ID sub-line and amber Pending chip; empty state text. Bell shows a dot and aria-expanded; outside click closes. | I8: GitHub / Linear / Jira (Atlassian) notification panel | J8: Lightweight awareness of contract and invoice events without leaving the current page; the unread toggle keeps the list to what still needs attention. | K8: "The bell carries the unread count and says whether its panel is open." | L8: js/core.js (renderNotif, toggleNotif), css/main.css (.np-*)
A9: 5 | B9: Global Shell | C9: App Frame | D9: Entity Switcher + Switch Entity page | E9: switch-entity | F9: Entity menu → Switch Entity; palette | G9: Multi-entity admins | H9: Header dropdown with entity card (logo tile, Entity ID, Type, Country). Full-screen .se-page on a dot-grid slate canvas with one centred card, explanation "Financial transactions will be filtered as per the selected entity", custom dropdown of entities (initials, ID · type, green "Current" pill), Cancel / Proceed. | I9: Slack / Notion workspace switcher; Stripe account picker; Vercel team picker (full-screen card on a dot grid) | J9: Switching entity changes every figure and record in the app, so it deserves a deliberate, focused step rather than a silent dropdown change. | K9: Ink for "the one thing that is yours"; the only colour on screen is the green Current pill. | L9: js/pages.js (buildSwitchEntityHTML), css/main.css (.se-*)
A10: 6 | B10: Global Shell | C10: App Frame | D10: My Profile | E10: my-profile | F10: User menu; Employee dashboard quick link | G10: Any signed-in user | H10: Hero card (initials avatar with verified tick, name, role badge, entity, Edit Profile) + underline tab bar: Basic Details, Bank Details, Attachments, Salary Slip, Change Password. Basic Details = left cards (Personal, Work, Security) + right cards (activity stats, notification toggles, recent activity timeline). Attachments = Requested Docs first, then uploaded grid and dashed "Not Uploaded" slots (click or drop). | I10: Google Account / GitHub profile settings (hero + tabs); Keka / greytHR "My Profile" document checklist; Gusto document-upload slots | J10: Employees self-serve their own data and documents in one place. Putting Requested Docs first answers "what is HR waiting on from me?" immediately. | K10: "A tab click changes a SECTION, not the page" — only the tab body repaints so the underline marker can travel. | L10: js/pages.js (buildMyProfileHTML), js/employee-lifecycle.js (Requested Docs)
A11: 7 | B11: Global Shell | C11: App Frame | D11: Agent Mode (AI assistant — empty & active) | E11: view agent-empty / agent-active | F11: openAgent() | G11: All users (admin persona) | H11: Empty: full-screen hero over a Three.js background, glass top bar "Agent Mode BETA", "What can I help you with?", two suggestion cards (Cost Calculator, Onboard an Employee), input with + menu and agent picker. Active: collapsed rail, 380px chat column (grey bot / navy user bubbles, typing dots) and a workspace column that renders the real stepper form or listing. | I11: ChatGPT / Claude new-chat screen (empty state); ChatGPT Canvas / Claude Artifacts (chat left, workspace right) | J11: Contract creation is a long structured form; conversation steers it while the workspace shows the editable artifact, avoiding forms rendered as chat bubbles. | K11: Workspace starts empty: "As you chat, I'll show relevant data, templates and previews on this side." | L11: index.html, js/core.js (agentMsgs, showAgentModule, buildQuickActions)
A12: 8 | B12: Overview | C12: Dashboard | D12: Dashboard shell — role tabs & shared widget system | E12: dashboard | F12: Sidebar → Dashboard | G12: All roles (demo switcher across 10 role views) | H12: Scrolling pill-tab strip with edge scroll buttons switches 10 role views. Shared parts: .hr-header, .hr-band (uppercase micro label + hairline + "Updated 5 min ago"), .hr-stat-grid KPI tiles (12-col grid, every tile spans 3, equal heights), .hr-actions Quick Actions panel, .hr-section panels with "View all ›". | I12: Rippling / Deel admin home + Stripe Dashboard KPI tiles; Polaris / Material affordance discipline for "door" tiles | J12: Each role sees the few numbers and actions that matter to their day. Identical tile sizes let the eye compare figures instead of reading size as importance; only tiles backed by a real list are clickable. | K12: "ONE CARD SIZE, EVERY DASHBOARD." A tile is a door "if, and only if, a listing exists" for it. Numbers are synced from data (syncDashCardCounts) — "a typed number is a claim nobody re-checks". Dates come from the clock. | L12: index.html, css/dashboard-multiview.css, js/core.js (DASH_CARD_LINK, syncDashCardCounts)
A13: 9 | B13: Overview | C13: Dashboard | D13: Employee Dashboard | E13: dashboard → tab "employee" | F13: Default dashboard tab | G13: Employee | H13: Welcome header → quick-link chips (My Profile, Policies, Leaves & Application, Holidays…) → lifecycle tracker → Overview band: Announcements (left, 2 rows), Attendance clock card, Leave Balance + Latest Payslip → Action Required table (Acknowledge / Submit / Update) → Payroll beside Leave Requests → Documents & Compliance (Form 16, Offer Letter) beside Upcoming timeline → navy "Need Help? Raise Ticket" banner. | I13: Keka / greytHR / Darwinbox employee home (clock-in, leave balance, payslip, Form 16, holidays) + BambooHR Home announcements feed | J13: Employees visit daily but briefly: one thing to do (punch in), a few things to read, a short to-do list. Indian-HRMS content (₹ payslips, Form 16, regional holidays) matches the user base. | K13: Latest Payslip is "the only payroll fact an employee acts on" — no Payroll Status tile. | L13: index.html (#employee-view), js/employee-lifecycle.js (empDashRender)
A14: 10 | B14: Overview | C14: Dashboard | D14: Attendance Clock-In / Clock-Out widget | E14: #att-card (Employee dashboard) | F14: Employee dashboard | G14: Employee | H14: One card with three resting states (idle, in, done). During a punch an SVG dial stage plays over the card: hands wind forward on clock-in, backward on clock-out; time readout rolls up. Location is required for clock-in (permission prompt, "Allow Location Access" recovery, padlock instructions if blocked). Daily total accumulates; aria-live announcement. | I14: Keka / greytHR web clock-in with geo-fencing; Apple Watch / iOS clock micro-animation | J14: Punching in is a daily, auditable, compliance-relevant action, so it gets strong feedback and must never fail silently. The fixed card size means the KPI grid never shifts. | K14: "Clocking in is the only thing on the employee dashboard the user DOES." "THE CARD NEVER RESIZES." "Attendance recorded without a location is attendance nobody can audit." | L14: js/renderer.js (ATT_T, _attRestore), css/main.css (.att)
A15: 11 | B15: Overview | C15: Dashboard | D15: Announcements panel + reading drawer | E15: Employee dashboard widget | F15: Employee dashboard | G15: Employee (authored by HR & managers) | H15: Panel with megaphone icon, count pill, newest 3 posts (initials avatar, title, author · role · time, blue New dot, amber pin), "View all +N more". Right 460px drawer with All / HR / Manager tabs, pinned first, full cards; opening a post scrolls and flashes it. Designed "You're all caught up" empty state. | I15: BambooHR / Workplace announcements feed; Notion / Intercom side-peek drawer; Linear inbox-zero empty state | J15: Read-mostly, low-frequency content: three items keep the dashboard cell fixed while the drawer handles long reads without leaving the dashboard. | K15: Empty box must not look like "this failed to load". Who someone is "is said in words", not by colour. | L15: js/announcements.js, css/announcements.css
A16: 12 | B16: Overview | C16: Dashboard | D16: Onboarding / Offboarding Tracker (employee) | E16: Employee dashboard widget | F16: Shown while a lifecycle runs | G16: Employee (new joiner / leaver) | H16: Section "Onboarding Tracker" with Current Status badge, big % and "X of Y stages", green progress bar, four 25% stage cards with sub-checklists, amber action row with "Upload Documents" only when the employee can act; pending lifecycle rows injected into Action Required with their owner. | I16: Deel / Remote.com worker onboarding progress; Rippling / Gusto onboarding checklist; Workday onboarding journey | J16: A new joiner needs progress and their single next action; work waiting on other teams is shown as status, not as tasks they cannot do. | K16: "FOUR STAGES, 25% EACH." "Only an action the employee can take gets a row here (FR-06)." | L16: js/employee-lifecycle.js (empDashTrackerHTML), js/dash-preview.js
... A92: 88 | B92: AI & Configure (hidden from sidebar) | C92: Prototype | D92: Log Demo (motion spec) | E92: log-demo.html | F92: Open file directly | G92: Design / dev team | H92: Standalone Teams listing demo: stat strip with spring count pops, split panel, add-log flow with custom dropdown, validation shake, row flash, self-closing success popup with hover-pausing progress bar. | I92: Material 3 motion tokens + Apple spring feedback (internal motion spec) | J92: A sandbox to agree motion behaviour before rolling it into the product. | K92: "Every colour, radius, duration and curve below is copied from css/main.css." Four durations, three curves. | L92: log-demo.html

Sheet Design System
A1: Standardised Design System
A2: Components and rules that every page reuses. Comments in the code repeatedly reject adding "a fifth dialect" — new screens are expected to be built from these parts.
A4: Component / pattern | B4: CSS / JS identifiers | C4: Standard specification | D4: Design reference — taken from | E4: Why it was standardised | F4: Used on
A5: Typography | B5: css/fonts.css, body in main.css | C5: Inter only, self-hosted (400–800), stylistic alternates cv02/cv03/cv04/cv11. Fixed scale with "no in-between sizes": metrics 22.5 / 18px, H1 18, H2 15, title 13, body 12, label & caption 11, micro 10px. Table heads 10.5px uppercase with .4px tracking. | D5: Linear / Vercel Geist / shadcn (Inter, tight neutral type) | E5: A small, fixed scale keeps dense HR tables readable and stops every screen inventing its own sizes. | F5: All pages
A6: Colour & ink | B6: --orange (#1a1a1a), --navy, --gray, slate ramp | C6: Monochrome UI: near-black ink as primary, slate-900 text, slate neutrals, white cards on #f8f9fb canvas. Colour is reserved for state. The token is still called --orange but holds #1a1a1a. | D6: Tailwind UI slate palette / shadcn "ink on white" | E6: When chrome is neutral, the few coloured things (status) carry meaning instantly. | F6: All pages
A7: Status tones | B7: --st-ok / wait / bad / info / idle; tone-*; .lp-status-badge, .ct-sb-badge | C7: Five tones only, each a bg / fg / border triple. Amber means "waiting", never "bad". ~60 status labels map to these tones through SB_STATUS_TONE. A badge that just changed pops once with the spring curve. | D7: Atlassian lozenges / Shopify Polaris badge tones | E7: One status vocabulary across modules — a Pending leave and a Pending contract look identical. | F7: Every listing, panel and dashboard
A8: Contract pipeline ladder | B8: --st-p1 … --st-p8 | C8: 8 stage colours (cyan → teal → blue → lime → violet → green → amber → deep green), documented as ΔE ≥ 12 apart and AA contrast. "The shade IS the data." | D8: HubSpot / Salesforce deal-stage colours (house-specific ladder) | E8: Contract progress can be read across a whole table from colour alone. | F8: Contracts listing, Ops dashboard
A9: Shape rule (pill vs square) | B9: --r-status 999px, --r-control 8px, --r-card 14px | C9: PILL = read-only state, never clickable. SQUARE (8px) = actionable (buttons, tabs, filters, dropdowns). Cards 14px, modals 16px. Inside forms all fields take 8px so neighbours agree. | D9: Material 3 shape tokens / Apple HIG affordance | E9: Users can tell what is clickable from shape alone. | F9: All pages
A10: Top bar | B10: .topbar, .tb-page-add, .tb-icon, .hdr-dd-* | C10: 56px white bar; page title + round "+" Add + contextual page tools; role switcher, Ctrl+K search, bell, entity and user menus on the right. | D10: Stripe Dashboard / Linear header | E10: Global controls in one predictable place; page-specific actions where the eye already is. | F10: All pages
A11: Sidebar rail | B11: .sidebar, .sb-section, .sb-parent, .sb-item, sbIco, sidebar-icons.css | C11: 224px → 62px icon rail; sections → accordion groups → children; 3px ink active bar; monochrome 15px icons with one-shot hover animation. | D11: Rippling / Deel IA + Atlassian side navigation | E11: Many modules, many roles: grouping by task keeps navigation learnable. | F11: All pages
A12: Filter bar | B12: .lp-filter-bar, .lp-search-input, apCS / .cs-trigger, .lp-pill-search | C12: "SELECT FILTER" label; search first, custom dropdowns, conditional "Clear Filters (n)", filled Search button; 34px controls. | D12: Ant Design ProTable search form / enterprise admin tables | E12: Explicit Search and Clear make multi-filter queries predictable for ops users. | F12: All listings
A13: Count tiles as filters | B13: .listing-stats, .listing-stat, .stat-selected | C13: Segmented strip of status counts; clicking toggles that status filter; selected tile gets grey fill + 3px ink bottom rail; counted over the whole set, not the filtered one. | D13: Zendesk / Freshdesk view counters; Polaris IndexTable view tabs | E13: Shows the distribution and doubles as the fastest filter. | F13: All listings, Compliance & CSM dashboards
A14: Listing table | B14: .lp-table, .lp-c-main/.lp-c-sub, .lp-action-btn, .lp-pagination, sticky-actions.js | C14: Sticky uppercase heads on #fafbfc, S.No first, pinned ACTION column (edge shadow only while content is hidden), 2-line cells, whole row clickable, grey hover / grey+ink-rail selection (never blue), staggered row entrance, "Showing x–y of z", 10 rows per page. | D14: Ant Design / DataTables admin table conventions | E14: Dense, scannable, familiar to Indian enterprise HR users; the pinned action never scrolls away. | F14: All listings
A15: Detail side panel | B15: .lp-split-sb, .lp-isb-tabbar, .sb-hero, .lp-sb-field-card, isbTab, sbRender | C15: Slides over 68% of the table; scrollable tabs Basic Details / Logs / History / (Attachments) / Workflow; hero card + 2-col field cards; status as coloured text (one coloured field per panel); tab kept when moving row to row; only the body swaps on tab change; draft dot + leave guard; render errors shown, never a blank sheet. | D15: Linear / Jira issue side panel; Rippling / Deel record view; Salesforce record tabs | E15: Users read one record without losing their place in the list; one panel grammar across every module. | F15: All listings
... A28: Responsive | B28: responsive.css | C28: Three steps: 1024 (rail auto-folds, tables scroll inside card, panel 88%), 640 (16px gutters, full-width panels, menus and toasts), filter bar & tiles wrap at 440px basis. | D28: Tailwind breakpoints approach | E28: "Each a real step down rather than a device" — layouts degrade predictably. | F28: All pages

Sheet Design Tokens
A1: Design Tokens (css/main.css, css/buttons.css, css/motion.css)
A2: Values as defined in the :root blocks. Swatch shows the background / main colour.
A4: Group | B4: Token | C4: Value | D4: Swatch | E4: Used for
A5: Core colour | B5: --orange (primary ink) | C5: #1a1a1a | E5: Primary brand ink — active states, primary buttons, rails. Name is legacy; no orange remains in the UI.
A6: Core colour | B6: --navy | C6: #0f172a | E6: Primary text
A7: Core colour | B7: --gray | C7: #6a7282 | E7: Secondary text, table heads
A8: Core colour | B8: --light | C8: #f8f9fb | E8: Page canvas
A9: Core colour | B9: --card | C9: #ffffff | E9: Cards, panels, modals
A10: Core colour | B10: --border | C10: #e5e7eb | E10: Hairlines, card borders, button strokes
A11: Core colour | B11: --ol | C11: #f1f5f9 | E11: Neutral chip / selected fill
A12: Core colour | B12: --red | C12: #ef4444 | E12: Required asterisk, error
A13: Buttons | B13: --btn-ink | C13: #353535 | E13: Primary button fill, outline label
A14: Buttons | B14: --btn-solid-hover | C14: #000000 | E14: Primary hover
A15: Status | B15: --st-ok (bg / fg / bd) | C15: #dcfce7 / #16a34a / #86efac | E15: Active, Approved, Paid, Connected
A16: Status | B16: --st-wait | C16: #fef3c7 / #92400e / #fde68a | E16: Pending, waiting — never "bad"
... A35: Motion | B35: --e-out / --e-in-out / --e-spring | C35: cubic-bezier(.22,1,.36,1) / (.65,0,.35,1) / (.34,1.4,.64,1) | E35: Entrances / moves / confirmations only

Sheet Reference Index
A1: Reference Index — where the designs come from
A2: Count column is a live COUNTIF over the "Design reference" column of the Page Design Map.
A4: Reference product / system | B4: Category | C4: What ADT borrows from it | D4: No. of pages citing it | E4: Pages that draw on it
A5: Deel | B5: Global EOR platform | C5: Product picker, global People view, Compliance Hub, cost calculator, contractor invoicing, onboarding progress, entity picker | D5: =COUNTIF('Page Design Map'!$I$5:$I$92,"*Deel*") -> 23 | E5: 1. Top Bar (title, page "+", role switcher, search, bell, entity, user menu) 2. Sidebar Navigation (grouped rail) 8. Dashboard shell — role tabs & shared widget system 12. Onboarding / Offboarding Tracker (employee) 15. Opendhi Super Admin Dashboard 16. OpenDhi Finance Admin Dashboard 21. Entity Owner Dashboard 23. Employees — Global Employee listing 26. Create New Employee wizard (4 steps) 28. Contracts Landing — type chooser 30. Contract Detail Panel + Status-move modal 31. Create a Contract — type chooser 32. EOR / PEO Contract wizard (3 steps) 33. Immigration Intake (3 steps) 34. Contractor Intake (3 steps) 35. Cost Calculator 60. Payroll — Pay Runs 62. Payments (Invoices) 63. Compliance Item (requirement catalogue) 64. Rates & Rules 65. Company Settings — listing + entity panel 72. Company Settings — Banking, Company Structure, Payroll tabs 82. AI Journey Run (guided live run)
A6: Remote.com | B6: Global EOR platform | C6: Add-worker wizards, country views, cost calculator, worker onboarding | D6: =COUNTIF('Page Design Map'!$I$5:$I$92,"*Remote.com*") -> 9 | E6: 12. Onboarding / Offboarding Tracker (employee) 15. Opendhi Super Admin Dashboard 23. Employees — Global Employee listing 26. Create New Employee wizard (4 steps) 28. Contracts Landing — type chooser 31. Create a Contract — type chooser 32. EOR / PEO Contract wizard (3 steps) 35. Cost Calculator 60. Payroll — Pay Runs
A7: Rippling | B7: HR / IT platform | C7: Sidebar IA, employee profile & record views, hire flow, role-permission preview, pay-run summary, app/access management | D7: =COUNTIF('Page Design Map'!$I$5:$I$92,"*Rippling*") -> 15 | E7: 2. Sidebar Navigation (grouped rail) 8. Dashboard shell — role tabs & shared widget system 12. Onboarding / Offboarding Tracker (employee) 22. Employees — Direct Employee listing 24. Employee Detail Panel 25. Employee Lifecycle — Logs tab & Add Log popup (onboarding / offboarding) 26. Create New Employee wizard (4 steps) 30. Contract Detail Panel + Status-move modal 39. AI journey — Employee / Proposal created, Waiting for approval 46. My Timesheet — month calendar ("soft tiles") 60. Payroll — Pay Runs 65. Company Settings — listing + entity panel 72. Company Settings — Banking, Company Structure, Payroll tabs 75. IT Accesses 82. AI Journey Run (guided live run)
A8: Keka | B8: Indian HRMS | C8: Attendance calendar, web clock-in, attendance requests, leave policies, team attendance, HR letters | D8: =COUNTIF('Page Design Map'!$I$5:$I$92,"*Keka*") -> 22 | E8: 6. My Profile 9. Employee Dashboard 10. Attendance Clock-In / Clock-Out widget 13. HR Dashboard 14. Reporting Manager (Team) Dashboard 22. Employees — Direct Employee listing 24. Employee Detail Panel 27. Teams listing + Create Team 41. HR Docs — landing catalogue 46. My Timesheet — month calendar ("soft tiles") 47. Timesheet Day panel + Manual entry 48. Attendance Request (claim on Weekly Off / Holiday) 49. Timesheet Export drawer 50. All Timesheet listing 51. Employee Timesheet view (read-only calendar) 52. Leave Requests 53. Apply Application (employee self-service) 55. Leave Balance — All balances 56. Leave Policies 59. View Optional Holidays (calendar overlay) 70. Company Settings — Leaves tab 71. Company Settings — Attendance tab (shift, grace, geofence)
A9: greytHR | B9: Indian HRMS | C9: Leave apply form (On Duty, Comp Off), regularisation, restricted holidays, leave balance ledger, payheads | D9: =COUNTIF('Page Design Map'!$I$5:$I$92,"*greytHR*") -> 14 | E9: 6. My Profile 9. Employee Dashboard 10. Attendance Clock-In / Clock-Out widget 24. Employee Detail Panel 41. HR Docs — landing catalogue 46. My Timesheet — month calendar ("soft tiles") 47. Timesheet Day panel + Manual entry 48. Attendance Request (claim on Weekly Off / Holiday) 53. Apply Application (employee self-service) 54. Leave Balance — My balance 56. Leave Policies 59. View Optional Holidays (calendar overlay) 61. Payheads 70. Company Settings — Leaves tab
A10: Darwinbox | B10: Indian HRMS | C10: Listing vocabulary (SR. NO, Select Filter), approval timeline, branch scoping, HR admin home | D10: =COUNTIF('Page Design Map'!$I$5:$I$92,"*Darwinbox*") -> 9 | E10: 9. Employee Dashboard 13. HR Dashboard 22. Employees — Direct Employee listing 27. Teams listing + Create Team 41. HR Docs — landing catalogue 52. Leave Requests 58. Holidays 71. Company Settings — Attendance tab (shift, grace, geofence) 72. Company Settings — Banking, Company Structure, Payroll tabs
A11: Zoho | B11: Indian HRMS / payroll | C11: Timesheet & leave listings, holiday lists, payroll components, inline master-data adds | D11: =COUNTIF('Page Design Map'!$I$5:$I$92,"*Zoho*") -> 8 | E11: 27. Teams listing + Create Team 50. All Timesheet listing 52. Leave Requests 54. Leave Balance — My balance 55. Leave Balance — All balances 58. Holidays 61. Payheads 72. Company Settings — Banking, Company Structure, Payroll tabs
A12: BambooHR | B12: HRIS | C12: Announcements feed, Who's out / celebrations, onboarding checklists, team masters | D12: =COUNTIF('Page Design Map'!$I$5:$I$92,"*BambooHR*") -> 6 | E12: 9. Employee Dashboard 11. Announcements panel + reading drawer 13. HR Dashboard 25. Employee Lifecycle — Logs tab & Add Log popup (onboarding / offboarding) 27. Teams listing + Create Team 58. Holidays
A13: Workday | B13: Enterprise HCM | C13: Manager self-service, onboarding journeys, payroll wage-type rules | D13: =COUNTIF('Page Design Map'!$I$5:$I$92,"*Workday*") -> 4 | E13: 12. Onboarding / Offboarding Tracker (employee) 14. Reporting Manager (Team) Dashboard 25. Employee Lifecycle — Logs tab & Add Log popup (onboarding / offboarding) 64. Rates & Rules
A14: Gusto | B14: SMB payroll / HR | C14: Pay-run summary, onboarding & document checklists | D14: =COUNTIF('Page Design Map'!$I$5:$I$92,"*Gusto*") -> 3 | E14: 6. My Profile 12. Onboarding / Offboarding Tracker (employee) 60. Payroll — Pay Runs
A15: HiBob | B15: HRIS | C15: People directory and side sheet | D15: =COUNTIF('Page Design Map'!$I$5:$I$92,"*HiBob*") -> 2 | E15: 22. Employees — Direct Employee listing 24. Employee Detail Panel
A16: Stripe | B16: Fintech dashboard | C16: Header, KPI tiles, setup guide, full-page forms, billing look, integration settings, account switcher | D16: =COUNTIF('Page Design Map'!$I$5:$I$92,"*Stripe*") -> 14 | E16: 1. Top Bar (title, page "+", role switcher, search, bell, entity, user menu) 5. Entity Switcher + Switch Entity page 8. Dashboard shell — role tabs & shared widget system 16. OpenDhi Finance Admin Dashboard 17. Finance Admin (Basic) Dashboard 20. Opendhi Ops Admin Dashboard 21. Entity Owner Dashboard 28. Contracts Landing — type chooser 33. Immigration Intake (3 steps) 35. Cost Calculator 57. Edit Leave Policy 62. Payments (Invoices) 64. Rates & Rules 67. Company Settings — E-Sign (DocuSeal) settings tab
A17: Linear | B17: Product tooling | C17: Command palette, list + peek panel, status menus, restraint & motion, empty states | D17: =COUNTIF('Page Design Map'!$I$5:$I$92,"*Linear*") -> 10 | E17: 1. Top Bar (title, page "+", role switcher, search, bell, entity, user menu) 3. Global Search / Command Palette (Ctrl+K) 4. Notifications Popover 11. Announcements panel + reading drawer 19. Opendhi Compliance Admin Dashboard (document review queue) 22. Employees — Direct Employee listing 25. Employee Lifecycle — Logs tab & Add Log popup (onboarding / offboarding) 29. Contracts Listing — pipeline table 30. Contract Detail Panel + Status-move modal 77. Tickets
A18: Jira | B18: Workflow / ITSM | C18: Transition screen with comment, owner-gated workflow, field history, notification panel, assets | D18: =COUNTIF('Page Design Map'!$I$5:$I$92,"*Jira*") -> 7 | E18: 4. Notifications Popover 19. Opendhi Compliance Admin Dashboard (document review queue) 22. Employees — Direct Employee listing 25. Employee Lifecycle — Logs tab & Add Log popup (onboarding / offboarding) 30. Contract Detail Panel + Status-move modal 74. Assets (asset allocation) 77. Tickets
A19: Atlassian | B19: Design system | C19: Side navigation mechanics, lozenge status tones, notification panel | D19: =COUNTIF('Page Design Map'!$I$5:$I$92,"*Atlassian*") -> 2 | E19: 2. Sidebar Navigation (grouped rail) 4. Notifications Popover
A20: Salesforce | B20: CRM | C20: Record tabs, deal pipeline, "Log in as", Agentforce | D20: =COUNTIF('Page Design Map'!$I$5:$I$92,"*Salesforce*") -> 5 | E20: 1. Top Bar (title, page "+", role switcher, search, bell, entity, user menu) 20. Opendhi Ops Admin Dashboard 29. Contracts Listing — pipeline table 65. Company Settings — listing + entity panel 87. AI Agents
A21: HubSpot | B21: CRM | C21: Deal-stage pipeline table | D21: =COUNTIF('Page Design Map'!$I$5:$I$92,"*HubSpot*") -> 2 | E21: 20. Opendhi Ops Admin Dashboard 29. Contracts Listing — pipeline table
A22: Zendesk | B22: Support desk | C22: Ticket statuses, Unassigned view, agent home | D22: =COUNTIF('Page Design Map'!$I$5:$I$92,"*Zendesk*") -> 2 | E22: 18. CSM Support Dashboard 77. Tickets
A23: Freshdesk | B23: Support desk | C23: Ticket queue counters, channel-agnostic queue | D23: =COUNTIF('Page Design Map'!$I$5:$I$92,"*Freshdesk*") -> 1 | E23: 77. Tickets
A24: Intercom | B24: Support / messaging | C24: Conversation states, chat-borne tickets with AI summary, side-peek drawer | D24: =COUNTIF('Page Design Map'!$I$5:$I$92,"*Intercom*") -> 4 | E24: 11. Announcements panel + reading drawer 18. CSM Support Dashboard 76. Chats 77. Tickets
A25: DocuSign | B25: E-signature | C25: Envelope tracking, template library, merge fields, review viewer | D25: =COUNTIF('Page Design Map'!$I$5:$I$92,"*DocuSign*") -> 7 | E25: 19. Opendhi Compliance Admin Dashboard (document review queue) 36. Contract Templates 40. AI journey — Contract document, Onboarding run, Journey complete 43. HR Docs — Create / Preview / Final letter flow 66. Company Settings — Attachments (MSA / NDA generation) 67. Company Settings — E-Sign (DocuSeal) settings tab 68. E-Sign — Send for signature & tracking
A26: PandaDoc | B26: Document automation | C26: Generate-from-template, live preview, template library | D26: =COUNTIF('Page Design Map'!$I$5:$I$92,"*PandaDoc*") -> 6 | E26: 36. Contract Templates 40. AI journey — Contract document, Onboarding run, Journey complete 43. HR Docs — Create / Preview / Final letter flow 44. HR Docs — Template editor (currently switched off) 66. Company Settings — Attachments (MSA / NDA generation) 68. E-Sign — Send for signature & tracking
A27: Vanta | B27: Compliance automation | C27: Control library and evidence review | D27: =COUNTIF('Page Design Map'!$I$5:$I$92,"*Vanta*") -> 2 | E27: 19. Opendhi Compliance Admin Dashboard (document review queue) 63. Compliance Item (requirement catalogue)
A28: Drata | B28: Compliance automation | C28: Evidence review queue | D28: =COUNTIF('Page Design Map'!$I$5:$I$92,"*Drata*") -> 1 | E28: 19. Opendhi Compliance Admin Dashboard (document review queue)
A29: Okta | B29: Identity / access | C29: User directory, role assignment, access reviews | D29: =COUNTIF('Page Design Map'!$I$5:$I$92,"*Okta*") -> 3 | E29: 69. Company Settings — Roles & Access tab 73. Users 75. IT Accesses
A30: ChatGPT | B30: AI assistant | C30: New-chat empty state, Canvas split (chat + workspace) | D30: =COUNTIF('Page Design Map'!$I$5:$I$92,"*ChatGPT*") -> 3 | E30: 7. Agent Mode (AI assistant — empty & active) 37. AI Contract Assistant (journey start) 38. AI-assisted Contract review (chat + pre-filled form)
A31: Copilot | B31: AI assistant | C31: Side-pane assistant, Copilot Studio agent catalogue | D31: =COUNTIF('Page Design Map'!$I$5:$I$92,"*Copilot*") -> 4 | E31: 37. AI Contract Assistant (journey start) 38. AI-assisted Contract review (chat + pre-filled form) 82. AI Journey Run (guided live run) 87. AI Agents
A32: Zapier | B32: Automation | C32: Journey catalogue, setup wizard, task history | D32: =COUNTIF('Page Design Map'!$I$5:$I$92,"*Zapier*") -> 4 | E32: 37. AI Contract Assistant (journey start) 78. AI Executive — journey catalogue 80. Automate Journey wizard 81. Active Automation + Run Detail
A33: UiPath | B33: Automation / RPA | C33: Human-in-the-loop action centre, recipe view | D33: =COUNTIF('Page Design Map'!$I$5:$I$92,"*UiPath*") -> 4 | E33: 38. AI-assisted Contract review (chat + pre-filled form) 39. AI journey — Employee / Proposal created, Waiting for approval 79. AI Journey Detail 86. Context & Journey + Journey detail
A34: Segment | B34: Data integration | C34: Workspace overview, sources, unified data models | D34: =COUNTIF('Page Design Map'!$I$5:$I$92,"*Segment *") -> 4 | E34: 67. Company Settings — E-Sign (DocuSeal) settings tab 83. Configure — Overview 84. Systems + System detail / Add system 85. Data Foundation + Model detail / Add model
A35: Google | B35: Productivity | C35: Calendar month grid, Docs page preview, Account profile, Admin directory | D35: =COUNTIF('Page Design Map'!$I$5:$I$92,"*Google*") -> 9 | E35: 6. My Profile 24. Employee Detail Panel 42. HR Docs — letter type screen 43. HR Docs — Create / Preview / Final letter flow 46. My Timesheet — month calendar ("soft tiles") 47. Timesheet Day panel + Manual entry 59. View Optional Holidays (calendar overlay) 69. Company Settings — Roles & Access tab 73. Users
A36: Notion | B36: Productivity | C36: Template gallery, side-peek, multi-select combobox, calendar styling | D36: =COUNTIF('Page Design Map'!$I$5:$I$92,"*Notion*") -> 6 | E36: 5. Entity Switcher + Switch Entity page 11. Announcements panel + reading drawer 25. Employee Lifecycle — Logs tab & Add Log popup (onboarding / offboarding) 41. HR Docs — landing catalogue 42. HR Docs — letter type screen 46. My Timesheet — month calendar ("soft tiles")
A37: Clockify | B37: Time tracking | C37: Weekly approval, report export | D37: =COUNTIF('Page Design Map'!$I$5:$I$92,"*Clockify*") -> 2 | E37: 46. My Timesheet — month calendar ("soft tiles") 49. Timesheet Export drawer
A38: Harvest | B38: Time tracking | C38: Week total & "submit week for approval" | D38: =COUNTIF('Page Design Map'!$I$5:$I$92,"*Harvest*") -> 2 | E38: 46. My Timesheet — month calendar ("soft tiles") 51. Employee Timesheet view (read-only calendar)
A39: Apple | B39: Design system (HIG) | C39: Segmented controls, spring feedback, clock animation | D39: =COUNTIF('Page Design Map'!$I$5:$I$92,"*Apple*") -> 3 | E39: 10. Attendance Clock-In / Clock-Out widget 45. Timesheets module (My / All tabs) 88. Log Demo (motion spec)
A40: Material 3 | B40: Design system | C40: Motion tokens, stepper, filter chips, shape tokens | D40: =COUNTIF('Page Design Map'!$I$5:$I$92,"*Material 3*") -> 3 | E40: 26. Create New Employee wizard (4 steps) 80. Automate Journey wizard 88. Log Demo (motion spec)
A41: Polaris | B41: Design system (Shopify) | C41: Badge tones, choice lists, setup checklist, full-page forms | D41: =COUNTIF('Page Design Map'!$I$5:$I$92,"*Polaris*") -> 4 | E41: 8. Dashboard shell — role tabs & shared widget system 21. Entity Owner Dashboard 26. Create New Employee wizard (4 steps) 57. Edit Leave Policy

Sheet Observations
A1: Observations & Follow-ups
A2: Inconsistencies found while analysing the project against its own standardised design rules. None were changed — this sheet is for review.
A4: # | B4: Observation | C4: Where | D4: Impact | E4: Suggested follow-up
A5: 1 | B5: AI Executive and Configure (cfg-*) pages have no sidebar entry; reachable only from inside AI flows. | C5: js/core.js sidebarItems; js/pages.js ~8758–11160 | D5: Twenty built pages are effectively hidden; the animated .sb-item-ai rail style is unused. | E5: Decide whether to re-link them (e.g. a Governance or Overview entry) or mark them as parked.
A6: 2 | B6: AI / cfg pages use the older .stat-card / .listing-table system with inline styles instead of hr-stat / lp-* components. | C6: js/pages.js AI & cfg builders | D6: They look like a different product next to the standard listing shell. | E6: Migrate to .hr-stat-card tiles and the lp-* listing when they are re-linked.
A7: 3 | B7: "Finance" sidebar dropdown holds only one page (Payments). | C7: js/core.js sidebarItems | D7: Breaks the stated rule "a dropdown only if it holds more than one page". | E7: Make Payments a direct item, or move it under Payroll Management.
A8: 4 | B8: Sidebar items carry a colour field that is never rendered. | C8: js/core.js sidebarItems (color:) | D8: Dead config; misleading to future editors. | E8: Remove the field or document it as reserved.
A9: 5 | B9: Token names say --orange but hold #1a1a1a (and legacy orange class names remain). | C9: css/main.css :root | D9: Confusing for new developers reading the CSS. | E9: Alias to --ink and keep --orange as a deprecated alias.
A10: 6 | B10: Chats is a listing with a state-machine panel, not a live inbox; the only bubble thread lives in Ticket → Conversation. | C10: js/pages.js buildChatsPageHTML | D10: If a real-time chat inbox is the product goal, this page does not provide it yet. | E10: Confirm intent; if needed add a thread pane modelled on the Ticket Conversation tab.
A11: 7 | B11: ctxMap (per-page agent context lines) is defined but never used. | C11: js/core.js ctxMap | D11: Dead code. | E11: Wire it into Agent Mode or remove it.
A12: 8 | B12: Stale comments: employee statuses described as "twelve" / "eight rungs" but the code now has four. | C12: js/pages.js ~330, ~368; js/employee-lifecycle.js EMP_STATUSES | D12: Misleads anyone using comments as the spec. | E12: Update the comments to the four-status + logs model.
A13: 9 | B13: Announcements comment says "no colour per person" but code still computes a per-name tone. | C13: js/announcements.js | D13: Small rule/code mismatch. | E13: Drop the tone computation or adjust the comment.
A14: 10 | B14: quick-actions.js / .css now hold the ticket-move confirm and pinned action column, not dashboard quick actions. | C14: js/quick-actions.js, css/quick-actions.css | D14: File names no longer describe their content. | E14: Rename (e.g. row-actions.js) when convenient.
A15: 11 | B15: Entity Setup Progress panel and pipeline cards still use inline styles; .setup-* and .pipeline-card CSS is unused. | C15: index.html entity-owner & ops views; css | D15: Dead CSS and off-system markup. | E15: Move the panel onto classes and delete the unused rules.
A16: 12 | B16: Two detail-header designs remain in CSS (.lp-sb-action-row in use, .lp-sb-record unrendered); .sb-hero is what renders. | C16: css/leaves.css ~120–145 | D16: Dead CSS. | E16: Remove the unused variant.
... A21: 17 | B21: Timesheet month grid uses the reversible "soft tiles" override. | C21: css/timesheet-calendar.css | D21: Intentional experiment; original design preserved. | E21: Remove the timesheet-calendar.css <link> in index.html to revert.
